pydepcheck/__init__.py
pydepcheck/analyzer.py
pydepcheck/dependences.py
pydepcheck/passes/expand_aug_assign.py
pydepcheck/passes/rewrite_range.py
pydepcheck-0.1.2.dist-info/LICENSE
pydepcheck-0.1.2.dist-info/METADATA
pydepcheck-0.1.2.dist-info/WHEEL
pydepcheck-0.1.2.dist-info/top_level.txt
pydepcheck-0.1.2.dist-info/RECORD
