Metadata-Version: 2.1
Name: pydepcheck
Version: 0.1.2
Summary: Analyze Python loop nest dependences.
Author-email: Tong Zhou <zt9465@gmail.com>
License: MIT License
License-File: LICENSE
